biosiglive/__init__.py
biosiglive/enums.py
biosiglive/file_io/__init__.py
biosiglive/file_io/save_and_load.py
biosiglive/gui/__init__.py
biosiglive/gui/plot.py
biosiglive/interfaces/__init__.py
biosiglive/interfaces/generic_interface.py
biosiglive/interfaces/param.py
biosiglive/interfaces/pytrigno_interface.py
biosiglive/interfaces/tcp_interface.py
biosiglive/interfaces/vicon_interface.py
biosiglive/processing/__init__.py
biosiglive/processing/compute_mvc.py
biosiglive/processing/data_processing.py
biosiglive/processing/msk_functions.py
biosiglive/streaming/__init__.py
biosiglive/streaming/client.py
biosiglive/streaming/server.py
biosiglive/streaming/stream_data.py
biosiglive/streaming/utils.py
biosiglive-2.0.3.dist-info/METADATA
biosiglive-2.0.3.dist-info/WHEEL
biosiglive-2.0.3.dist-info/licenses/LICENSE
biosiglive-2.0.3.dist-info/RECORD
