Metadata-Version: 2.1
Name: biosiglive
Version: 2.0.3
Summary: Biosignal processing and visualization in real-time.
Project-URL: Homepage, https://github.com/pyomeca/biosiglive
Project-URL: Bug Tracker, https://github.com/pyomeca/biosiglive/issues
Author-email: Amedeo ceglia <amedeo.ceglia@umontreal.ca>
License-File: LICENSE
Classifier: License :: OSI Approved :: MIT License
Classifier: Operating System :: OS Independent
Classifier: Programming Language :: Python :: 3
Requires-Python: >=3.8
Requires-Dist: matplotlib
Requires-Dist: numpy
Requires-Dist: scipy
